[
  {
    "question": "教室に赤いりんごが3つと、青いりんごが2つあります。りんごは全部で何個ありますか？",
    "options": [
      "5個",
      "4個",
      "6個",
      "3個"
    ],
    "hint": "赤いりんごと青いりんごを合わせて数えてみましょう。",
    "explanation": "赤いりんごが3個と青いりんごが2個あります。3 + 2 = 5なので、りんごは全部で5個です。",
    "correct_answer_index": 0
  },
  {
    "question": "公園で子どもたちが遊んでいます。女の子が2人、男の子が3人います。子どもたちは全部で何人いますか？",
    "options": [
      "4人",
      "5人",
      "6人",
      "3人"
    ],
    "hint": "女の子と男の子を合わせて数えてみましょう。",
    "explanation": "女の子が2人と男の子が3人います。2 + 3 = 5なので、子どもたちは全部で5人います。",
    "correct_answer_index": 1
  },
  {
    "question": "花だんに花が4本さいています。2本新しく植えました。花は全部で何本になりましたか？",
    "options": [
      "5本",
      "7本",
      "6本",
      "3本"
    ],
    "hint": "もともとあった花の数に、新しく植えた花の数を足してみましょう。",
    "explanation": "はじめに4本あって、新しく2本植えました。4 + 2 = 6なので、花は全部で6本になりました。",
    "correct_answer_index": 2
  }
]